{
  "_format": "hh-sol-cache-2",
  "files": {
    "/home/saint/all_code/playground/frontend/airdrop_launchpad/contracts/Dummy.sol": {
      "lastModificationDate": 1753303958581,
      "contentHash": "a83822760f98d00ad46061fa2e6f50ab",
      "sourceName": "contracts/Dummy.sol",
      "solcConfig": {
        "version": "0.8.28",
        "settings": {
          "evmVersion": "paris",
          "optimizer": {
            "enabled": false,
            "runs": 200
          },
          "outputSelection": {
            "*": {
              "*": [
                "abi",
                "evm.bytecode",
                "evm.deployedBytecode",
                "evm.methodIdentifiers",
                "metadata"
              ],
              "": [
                "ast"
              ]
            }
          }
        }
      },
      "imports": [],
      "versionPragmas": [
        ">=0.8.2 <0.9.0"
      ],
      "artifacts": [
        "Dummy"
      ]
    }
  }
}
